snitch2/__init__.py
snitch2/exceptions.py
snitch2/parselink.py
snitch2/snitch2.py
snitch2-0.3.0.dist-info/DESCRIPTION.rst
snitch2-0.3.0.dist-info/METADATA
snitch2-0.3.0.dist-info/metadata.json
snitch2-0.3.0.dist-info/RECORD
snitch2-0.3.0.dist-info/top_level.txt
snitch2-0.3.0.dist-info/WHEEL
